eyeballvul/__init__.py
eyeballvul/api.py
eyeballvul/cli.py
eyeballvul/config/__init__.py
eyeballvul/config/config.toml
eyeballvul/config/config_loader.py
eyeballvul/converter.py
eyeballvul/exceptions.py
eyeballvul/models/__init__.py
eyeballvul/models/cache.py
eyeballvul/models/common.py
eyeballvul/models/eyeballvul.py
eyeballvul/models/osv.py
eyeballvul/py.typed
eyeballvul/score.py
eyeballvul/util.py
eyeballvul-0.7.0.dist-info/LICENSE
eyeballvul-0.7.0.dist-info/METADATA
eyeballvul-0.7.0.dist-info/WHEEL
eyeballvul-0.7.0.dist-info/entry_points.txt
eyeballvul-0.7.0.dist-info/RECORD
