Metadata-Version: 2.1
Name: eyeballvul
Version: 0.7.0
Summary: 
Author: Timothee Chauvin
Author-email: timothee.chauvin28@gmail.com
Requires-Python: >=3.10,<4.0
Classifier: Programming Language :: Python :: 3
Classifier: Programming Language :: Python :: 3.10
Classifier: Programming Language :: Python :: 3.11
Requires-Dist: fire (>=0.6.0,<0.7.0)
Requires-Dist: litellm (>=1.37.12,<2.0.0)
Requires-Dist: ortools (>=9.9.3963,<10.0.0)
Requires-Dist: pydantic (>=2.7.1,<3.0.0)
Requires-Dist: requests (>=2.31.0,<3.0.0)
Requires-Dist: sqlmodel (>=0.0.18,<0.0.19)
Requires-Dist: tomli (>=2.0.1,<3.0.0)
Requires-Dist: typeguard (>=4.2.1,<5.0.0)
Requires-Dist: types-pyyaml (>=6.0.12.20240311,<7.0.0.0)
